swarms_rust/__init__.py
swarms_rust-0.1.1.dist-info/LICENSE
swarms_rust-0.1.1.dist-info/METADATA
swarms_rust-0.1.1.dist-info/WHEEL
swarms_rust-0.1.1.dist-info/RECORD
