Metadata-Version: 2.1
Name: swarms-rust
Version: 0.1.1
Summary: A Rust-powered Python extension for concurrency, file I/O, and async API requests.
Home-page: https://github.com/the-swarms-corporation/swarms-rust
License: MIT
Author: Kye Gomez
Author-email: kye@kyegomez.com
Requires-Python: >=3.10,<4.0
Classifier: License :: OSI Approved :: MIT License
Classifier: Programming Language :: Python :: 3
Classifier: Programming Language :: Python :: 3.10
Classifier: Programming Language :: Python :: 3.11
Classifier: Programming Language :: Python :: 3.12
Project-URL: Repository, https://github.com/the-swarms-corporation/swarms-rust
